engineering_calculator/__init__.py
engineering_calculator/actions.py
engineering_calculator/calculator.py
engineering_calculator/main.py
engineering_calculator-1.11.dist-info/entry_points.txt
engineering_calculator-1.11.dist-info/WHEEL
engineering_calculator-1.11.dist-info/METADATA
engineering_calculator-1.11.dist-info/RECORD
