Metadata-Version: 2.1
Name: engineering-calculator
Version: 1.11
Summary: Engineering RPN calculator.
Keywords: calculator,RPN
Author: Ken Kundert
Author-email: ec@nurdletech.com
Requires-Python: >=3.6
Classifier: Development Status :: 5 - Production/Stable
Classifier: Intended Audience :: Science/Research
Classifier: License :: OSI Approved :: GNU General Public License v3 or later (GPLv3+)
Classifier: Natural Language :: English
Classifier: Operating System :: POSIX :: Linux
Classifier: Programming Language :: Python :: 3
Classifier: Topic :: Utilities
Requires-Dist: docopt
Requires-Dist: docutils
Requires-Dist: inform
Requires-Dist: quantiphy
Requires-Dist: requests
Project-URL: changelog, https://engineering-calculator.readthedocs.io/en/latest/releases.html
Project-URL: documentation, https://engineering-calculator.readthedocs.io
Project-URL: homepage, https://engineering-calculator.readthedocs.io
Project-URL: repository, https://github.com/kenkundert/ec
